<?xml version="1.0" encoding="utf-8" ?><dwsync><file name="lan_admin.php" server="esagonale.it/esagonale.it/" local="3441288640" remote="318763443807939312" Dst="-1" /><file name="lan_admin_log.php" server="esagonale.it/esagonale.it/" local="3441288640" remote="318763443807939312" Dst="-1" /><file name="lan_administrator.php" server="esagonale.it/esagonale.it/" local="3441288640" remote="318763443807939312" Dst="-1" /><file name="lan_banlist.php" server="esagonale.it/esagonale.it/" local="3441288640" remote="318763443807939312" Dst="-1" /><file name="lan_banner.php" server="esagonale.it/esagonale.it/" local="3441288640" remote="318763443807939312" Dst="-1" /><file name="lan_cache.php" server="esagonale.it/esagonale.it/" local="3441288640" remote="318763443807939312" Dst="-1" /><file name="lan_check_user.php" server="esagonale.it/esagonale.it/" local="3441288640" remote="318763443807939312" Dst="-1" /><file name="lan_content.php" server="esagonale.it/esagonale.it/" local="3441288640" remote="318763443807939312" Dst="-1" /><file name="lan_cpage.php" server="esagonale.it/esagonale.it/" local="3441288640" remote="318763443807939312" Dst="-1" /><file name="lan_credits.php" server="esagonale.it/esagonale.it/" local="3441288640" remote="318763443807939312" Dst="-1" /><file name="lan_custommenu.php" server="esagonale.it/esagonale.it/" local="3441288640" remote="318763443807939312" Dst="-1" /><file name="lan_db.php" server="esagonale.it/esagonale.it/" local="3441288640" remote="318763443807939312" Dst="-1" /><file name="lan_docs.php" server="esagonale.it/esagonale.it/" local="3441288641" remote="318763443807939312" Dst="-1" /><file name="lan_db_verify.php" server="esagonale.it/esagonale.it/" local="3441288641" remote="318763443807939312" Dst="-1" /><file name="lan_download.php" server="esagonale.it/esagonale.it/" local="3441288641" remote="318763443807939312" Dst="-1" /><file name="lan_e107_update.php" server="esagonale.it/esagonale.it/" local="3441288641" remote="318763443807939312" Dst="-1" /><file name="lan_emoticon.php" server="esagonale.it/esagonale.it/" local="3441288641" remote="318763443807939312" Dst="-1" /><file name="lan_fileinspector.php" server="esagonale.it/esagonale.it/" local="3441288641" remote="318763443807939312" Dst="-1" /><file name="lan_filemanager.php" server="esagonale.it/esagonale.it/" local="3441288641" remote="318763443807939312" Dst="-1" /><file name="lan_fla.php" server="esagonale.it/esagonale.it/" local="3441288641" remote="318763443807939312" Dst="-1" /><file name="lan_footer.php" server="esagonale.it/esagonale.it/" local="3441288641" remote="318763443807939312" Dst="-1" /><file name="lan_frontpage.php" server="esagonale.it/esagonale.it/" local="3441288641" remote="318763443807939312" Dst="-1" /><file name="lan_header.php" server="esagonale.it/esagonale.it/" local="3441288641" remote="318763443807939312" Dst="-1" /><file name="lan_image.php" server="esagonale.it/esagonale.it/" local="3441288641" remote="318763443807939312" Dst="-1" /><file name="lan_lancheck.php" server="esagonale.it/esagonale.it/" local="3441288641" remote="318763443807939312" Dst="-1" /><file name="lan_language.php" server="esagonale.it/esagonale.it/" local="3441288641" remote="318763443807939312" Dst="-1" /><file name="lan_links.php" server="esagonale.it/esagonale.it/" local="3441288641" remote="318763443807939312" Dst="-1" /><file name="lan_mailout.php" server="esagonale.it/esagonale.it/" local="3441288641" remote="318763443807939312" Dst="-1" /><file name="lan_menus.php" server="esagonale.it/esagonale.it/" local="3441288641" remote="318763443807939312" Dst="-1" /><file name="lan_message.php" server="esagonale.it/esagonale.it/" local="3441288641" remote="318763443807939312" Dst="-1" /><file name="lan_meta.php" server="esagonale.it/esagonale.it/" local="3441288641" remote="318763443807939312" Dst="-1" /><file name="lan_modcomment.php" server="esagonale.it/esagonale.it/" local="3441288642" remote="318763443807939312" Dst="-1" /><file name="lan_newspost.php" server="esagonale.it/esagonale.it/" local="3441288642" remote="318763443807939312" Dst="-1" /><file name="lan_notify.php" server="esagonale.it/esagonale.it/" local="3441288642" remote="318763443807939312" Dst="-1" /><file name="lan_plugin.php" server="esagonale.it/esagonale.it/" local="3441288642" remote="318763443807939312" Dst="-1" /><file name="lan_review.php" server="esagonale.it/esagonale.it/" local="3441288642" remote="318763443807939312" Dst="-1" /><file name="lan_prefs.php" server="esagonale.it/esagonale.it/" local="3441288642" remote="318763443807939312" Dst="-1" /><file name="lan_search.php" server="esagonale.it/esagonale.it/" local="3441288642" remote="318763443807939312" Dst="-1" /><file name="lan_theme.php" server="esagonale.it/esagonale.it/" local="3441288642" remote="318763443807939312" Dst="-1" /><file name="lan_ugflag.php" server="esagonale.it/esagonale.it/" local="3441288642" remote="318763443807939312" Dst="-1" /><file name="lan_updateadmin.php" server="esagonale.it/esagonale.it/" local="3441288642" remote="318763443807939312" Dst="-1" /><file name="lan_upload.php" server="esagonale.it/esagonale.it/" local="3441288642" remote="318763443807939312" Dst="-1" /><file name="lan_userclass.php" server="esagonale.it/esagonale.it/" local="3441288642" remote="318763443807939312" Dst="-1" /><file name="lan_userclass2.php" server="esagonale.it/esagonale.it/" local="3441288642" remote="318763443807939312" Dst="-1" /><file name="lan_userinfo.php" server="esagonale.it/esagonale.it/" local="3441288642" remote="318763443807939312" Dst="-1" /><file name="lan_users.php" server="esagonale.it/esagonale.it/" local="3441288642" remote="318763443807939312" Dst="-1" /><file name="lan_users_extended.php" server="esagonale.it/esagonale.it/" local="3441288642" remote="318763443807939312" Dst="-1" /><file name="lan_wmessage.php" server="esagonale.it/esagonale.it/" local="3441288642" remote="318763443807939312" Dst="-1" /></dwsync>